deltachat_chatbot/__init__.py
deltachat_chatbot/__main__.py
deltachat_chatbot/gpt4all.py
deltachat_chatbot/hooks.py
deltachat_chatbot-0.3.0.dist-info/LICENSE
deltachat_chatbot-0.3.0.dist-info/METADATA
deltachat_chatbot-0.3.0.dist-info/WHEEL
deltachat_chatbot-0.3.0.dist-info/entry_points.txt
deltachat_chatbot-0.3.0.dist-info/top_level.txt
deltachat_chatbot-0.3.0.dist-info/RECORD
